pplx_api/__init__.py
pplx_api/pplx_api.py
pplx_api-0.1.5.dist-info/LICENSE
pplx_api-0.1.5.dist-info/METADATA
pplx_api-0.1.5.dist-info/WHEEL
pplx_api-0.1.5.dist-info/top_level.txt
pplx_api-0.1.5.dist-info/RECORD
