Metadata-Version: 2.2
Name: pplx_api
Version: 0.1.5
Summary: A Python client for the Perplexity AI API
Home-page: https://github.com/kamiwaza-ai/pplx_api
Author: Kamiwaza AI
Author-email: opensource@kamiwaza.ai
Classifier: Development Status :: 3 - Alpha
Classifier: Intended Audience :: Developers
Classifier: License :: OSI Approved :: MIT License
Classifier: Programming Language :: Python :: 3
Classifier: Programming Language :: Python :: 3.10
Classifier: Programming Language :: Python :: 3.11
Classifier: Programming Language :: Python :: 3.12
Requires-Python: >=3.10
License-File: LICENSE
Requires-Dist: requests>=2.31.0
Requires-Dist: pydantic>=2.5.2
Requires-Dist: aiohttp>=3.8.5
Dynamic: author
Dynamic: author-email
Dynamic: classifier
Dynamic: description
Dynamic: description-content-type
Dynamic: home-page
Dynamic: requires-dist
Dynamic: requires-python
Dynamic: summary
